ads1118/__init__.py
ads1118/ads1118.py
ads1118-1.1.dist-info/LICENSE
ads1118-1.1.dist-info/METADATA
ads1118-1.1.dist-info/WHEEL
ads1118-1.1.dist-info/top_level.txt
ads1118-1.1.dist-info/RECORD
