Metadata-Version: 2.1
Name: ads1118
Version: 1.1
Summary: Python library for the ADS1118 4-channel ADC
Home-page: UNKNOWN
Author: David Krywult
Author-email: dak1st@gmx.at
License: MIT
Keywords: Raspberry Pi
Platform: UNKNOWN
Classifier: Development Status :: 5 - Production/Stable
Classifier: Operating System :: POSIX :: Linux
Classifier: License :: OSI Approved :: MIT License
Classifier: Intended Audience :: Developers
Classifier: Programming Language :: Python :: 2.7
Classifier: Programming Language :: Python :: 3
Classifier: Topic :: Software Development
Classifier: Topic :: System :: Hardware
Requires-Dist: spidev (>=3.4)
